simpleutilz/Definition.py
simpleutilz/ListOfColours.py
simpleutilz/__init__.py
simpleutilz/simpleColours.py
simpleutilz/simpleutilz.py
simpleutilz-1.1.7.dist-info/LICENSE
simpleutilz-1.1.7.dist-info/METADATA
simpleutilz-1.1.7.dist-info/WHEEL
simpleutilz-1.1.7.dist-info/top_level.txt
simpleutilz-1.1.7.dist-info/RECORD
