Metadata-Version: 2.1
Name: simpleutilz
Version: 1.1.7
Summary: A versatile Python utility library that offers a wide range of helper functions, classes, and modules to expedite development tasks and simplify common operations
Home-page: https://github.com/ItzSimplyJoe/SimpleUtilz
Author: ItzSimplyJoe
Author-email: joebostock30@gmail.com
Classifier: Development Status :: 5 - Production/Stable
Classifier: License :: OSI Approved :: MIT License
Classifier: Programming Language :: Python :: 3
Classifier: Programming Language :: Python :: 3.6
Classifier: Programming Language :: Python :: 3.7
Classifier: Programming Language :: Python :: 3.8
Classifier: Programming Language :: Python :: 3.9
Classifier: Operating System :: OS Independent
License-File: LICENSE
Requires-Dist: requests
Requires-Dist: PyPDF2
Requires-Dist: cryptography
